{
  "Thẻ_SIM": "1 nano sim",
  "Màn_hình": "4.7 inches, IPS LCD",
  "Độ_phân_giải": "750 x 1334 pixels, tỷ lệ 16:9",
  "CPU": "Apple A9",
  "RAM": "2GB",
  "Bộ_nhớ_Thẻ_nhớ": "16GB / 32GB / 64GB /128GB",
  "Camera_sau": "12 MP, f/2.2, 4K@30fps, 1080p@60fps",
  "Camera_trước": "5 MP, f/2.2, HDR, panorama, 720p@30fps",
  "Jack_Loa": "Có/ Loa đơn",
  "Pin": "1715 mAh",
  "Màu_sắc": ["Xám", "Bạc", "Hồng", "Vàng"],
  "GPU": "PowerVR GT7600",
  "Ngày_ra_mắt": "25/9/2015",
  "Hệ_điều_hành": "iOS 15",
  "Loại_sản_phẩm": "Cũ QSD, nguyên bản",
  "Mạng_Băng_tần": "GSM / CDMA / HSPA / EVDO / LTE",
  "Kích_thước": "138.3 x 67.1 x 7.1 mm",
  "Trọng_lượng": "143 g",
  "Bluetooth": "4.2, A2DP, LE",
  "Chuẩn_bộ_nhớ": "NVMe",
  "Chuẩn_âm_thanh": "16-bit/44.1kHz audio",
  "Wifi": "802.11 a/b/g/n/ac, dual-band",
  "NFC": "Có",
  "Cổng_kết_nối": "Lightning"
}
