{
  "Thẻ_SIM": "Nano + eSim",
  "Màn_hình": "6.1 inches, Super Retina XDR OLED, 120Hz, HDR10",
  "Độ_phân_giải": "1170 x 2532 pixels, tỷ lệ 19.5:9",
  "CPU": "Apple A15 Bionic (5 nm)",
  "RAM": "6GB",
  "Bộ_nhớ_Thẻ_nhớ": "128/256/512GB/1TB",
  "Camera_sau": "Triple 12 MP, f/1.5 - 12MP - 12MP",
  "Camera_trước": "12 MP, f/2.2",
  "Jack_Loa": "Không/ Loa kép Stereo",
  "Pin": "3095mAh, sạc nhanh 23W",
  "Màu_sắc": ["Xanh", "Xám", "Vàng", "Trắng"],
  "GPU": "Apple GPU (5-core graphics)",
  "Ngày_ra_mắt": "24/9/2021",
  "Hệ_điều_hành": "iOS 15",
  "Loại_sản_phẩm": "Chưa kích hoạt",
  "Mạng_Băng_tần": "GSM / CDMA / HSPA / EVDO / LTE / 5G",
  "Kích_thước": "146.7 x 71.5 x 7.7 mm",
  "Trọng_lượng": "204 g",
  "Bluetooth": "5.0, A2DP, LE",
  "Chuẩn_bộ_nhớ": "NVMe",
  "Chuẩn_âm_thanh": "24-bit/192kHz audio",
  "Wifi": "802.11 a/b/g/n/ac/6, dual-band",
  "NFC": "Có",
  "Cổng_kết_nối": "Lightning"
}
